cz_lazycommit.py
cz_lazycommit-1.3.2.dist-info/METADATA
cz_lazycommit-1.3.2.dist-info/WHEEL
cz_lazycommit-1.3.2.dist-info/entry_points.txt
cz_lazycommit-1.3.2.dist-info/top_level.txt
cz_lazycommit-1.3.2.dist-info/RECORD
