Metadata-Version: 2.4
Name: cz-lazycommit
Version: 1.3.2
Summary: A Commitizen plugin that integrates with lazycommit CLI tool to generate AI-powered commit messages
License: MIT License
Project-URL: Homepage, https://github.com/lazycommit/cz-lazycommit
Project-URL: Source, https://github.com/lazycommit/cz-lazycommit
Project-URL: Issue Tracker, https://github.com/lazycommit/cz-lazycommit/issues
Project-URL: Repository, https://github.com/lazycommit/cz-lazycommit
Requires-Python: >=3.7
Requires-Dist: commitizen
Requires-Dist: prompt-toolkit
